.DS_Store
.gitattributes
.gitignore
CONTRIBUTION.md
LICENSE
README.md
makefile
pyproject.toml
setup.py
.github/workflows/build_docs.yaml
.github/workflows/pypi_push.yaml
.github/workflows/pytest.yaml
benchmarks/batch_generation.py
benchmarks/inner_nodes_est_R.ipynb
benchmarks/phylmean.py
benchmarks/phylogenetic_mean.ipynb
docs/Makefile
docs/make.bat
docs/figures/hyperiax_logo.png
docs/figures/hyperiax_logo_small.png
docs/source/conf.py
docs/source/hyperiax.execution.rst
docs/source/hyperiax.mcmc.rst
docs/source/hyperiax.models.functional.rst
docs/source/hyperiax.models.prebuilts.rst
docs/source/hyperiax.models.rst
docs/source/hyperiax.rst
docs/source/hyperiax.tree.rst
docs/source/index.rst
docs/source/usage.rst
docs/source/generated/tree.rst
docs/source/notebooks/DICAROS.ipynb
docs/source/notebooks/Upwards_LDDMM.ipynb
docs/source/notebooks/mcmc_Gaussian_BFFG.ipynb
docs/source/notebooks/mcmc_Gaussian_BFFG_shapes.ipynb
docs/source/notebooks/mean_estimation.ipynb
docs/source/notebooks/tree_building.ipynb
examples/ABFFG.py
examples/DICAROS.ipynb
examples/SDE.py
examples/Tree building.ipynb
examples/__init__.py
examples/fast.ipynb
examples/localfast.ipynb
examples/mcmc_Gaussian_BFFG.ipynb
examples/mcmc_Gaussian_BFFG_shapes.ipynb
examples/mcmc_Gaussian_BFFG_shapes_SDEs.ipynb
examples/mcmc_Gaussian_BFFG_shapes_SDEs_3D.ipynb
examples/mcmc_Gaussian_BFFG_shapes_state-dependent_covariance.ipynb
examples/mcmc_Gaussian_BFFG_shapes_state-dependent_covariance_3D.ipynb
examples/mean_estimation.ipynb
examples/shape.py
hyperiax/__init__.py
hyperiax/_version.py
hyperiax.egg-info/PKG-INFO
hyperiax.egg-info/SOURCES.txt
hyperiax.egg-info/dependency_links.txt
hyperiax.egg-info/requires.txt
hyperiax.egg-info/top_level.txt
hyperiax/execution/__init__.py
hyperiax/execution/fastexecutor.py
hyperiax/execution/unorderedexecutor.py
hyperiax/mcmc/__init__.py
hyperiax/mcmc/fixedparameter.py
hyperiax/mcmc/metropolis_hastings.py
hyperiax/mcmc/parameter.py
hyperiax/mcmc/parameterstore.py
hyperiax/mcmc/plotting.py
hyperiax/mcmc/statistics.py
hyperiax/mcmc/varianceParameter.py
hyperiax/models/__init__.py
hyperiax/models/basemodel.py
