Metadata-Version: 2.1
Name: hyperiax
Version: 2.0.2
Summary: Tree traversals using JAX
Author-email: Stefan Sommer <sommer@di.ku.dk>, Marcus Holte Teller <marcus@di.ku.dk>, Gefan Yang <***@di.ku.dk>, Michael Baand Severinsen <***@di.ku.dk>, Morten Akhøj Pedersen <***@di.ku.dk>, Nicklas Boserup <***@di.ku.dk>
Project-URL: Homepage, https://github.com/computationalevolutionarymorphometry/hyperiax
Project-URL: Issues, https://github.com/computationalevolutionarymorphometry/hyperiax/issues
Classifier: Programming Language :: Python :: 3
Classifier: License :: OSI Approved :: Apache Software License
Classifier: Operating System :: OS Independent
Requires-Python: >=3.8
Provides-Extra: examples
Provides-Extra: dev
Provides-Extra: doc
License-File: LICENSE
